tapdance/__init__.py
tapdance/cli.py
tapdance/config.py
tapdance/docker.py
tapdance/install_helper.py
tapdance/plans.py
tapdance/states.py
tapdance/syncs.py
slalom_tapdance-1.0.3.dist-info/LICENSE
slalom_tapdance-1.0.3.dist-info/METADATA
slalom_tapdance-1.0.3.dist-info/WHEEL
slalom_tapdance-1.0.3.dist-info/entry_points.txt
slalom_tapdance-1.0.3.dist-info/RECORD
